shellforgepy/__init__.py
shellforgepy/__main__.py
shellforgepy/simple.py
shellforgepy/adapters/_adapter.py
shellforgepy/adapters/_adapter_bridge.py
shellforgepy/adapters/adapter_chooser.py
shellforgepy/adapters/font_resolver.py
shellforgepy/adapters/cadquery/cadquery_adapter.py
shellforgepy/adapters/freecad/freecad_adapter.py
shellforgepy/construct/alignment.py
shellforgepy/construct/alignment_operations.py
shellforgepy/construct/bounding_box_helpers.py
shellforgepy/construct/construct_utils.py
shellforgepy/construct/cylinder_spec.py
shellforgepy/construct/leader_followers_cutters_part.py
shellforgepy/construct/named_part.py
shellforgepy/construct/part_collector.py
shellforgepy/construct/part_parameters.py
shellforgepy/construct/polygon_spec.py
shellforgepy/construct/step_serialization.py
shellforgepy/geometry/__init__.py
shellforgepy/geometry/face_point_cloud.py
shellforgepy/geometry/higher_order_solids.py
shellforgepy/geometry/m_screws.py
shellforgepy/geometry/mesh_builders.py
shellforgepy/geometry/mesh_utils.py
shellforgepy/geometry/modifications.py
shellforgepy/geometry/sheet_metal.py
shellforgepy/geometry/spherical_tools.py
shellforgepy/geometry/treapezoidal_snake_geometry.py
shellforgepy/produce/arrange_and_export.py
shellforgepy/produce/production_parts_model.py
shellforgepy/shells/connector_hint.py
shellforgepy/shells/connector_utils.py
shellforgepy/shells/materialized_connectors.py
shellforgepy/shells/mesh_partition.py
shellforgepy/shells/partitionable_spheroid_triangle_mesh.py
shellforgepy/shells/paths.py
shellforgepy/shells/polygon_perforation.py
shellforgepy/shells/region_edge_feature.py
shellforgepy/shells/transformed_region_view.py
shellforgepy/slicing/orca_slicer_settings_generator.py
shellforgepy/workflow/preview_generator.py
shellforgepy/workflow/upload_to_printer.py
shellforgepy/workflow/workflow.py
shellforgepy-3.3.0.dist-info/licenses/LICENSE.txt
shellforgepy-3.3.0.dist-info/METADATA
shellforgepy-3.3.0.dist-info/WHEEL
shellforgepy-3.3.0.dist-info/top_level.txt
shellforgepy-3.3.0.dist-info/RECORD
