Metadata-Version: 2.4
Name: shellforgepy
Version: 3.3.0
Summary: Python tooling for backend-agnostic 3D modeling and fabrication
Home-page: https://github.com/m-emm/shellforgepy
Author: Markus Emmenegger
Author-email: markus.emmenegger@poemai.ch
License: MIT
Project-URL: Documentation, https://github.com/m-emm/shellforgepy/blob/main/README.md
Project-URL: Source, https://github.com/m-emm/shellforgepy
Project-URL: Changelog, https://github.com/m-emm/shellforgepy/blob/main/CHANGELOG.md
Project-URL: Tracker, https://github.com/m-emm/shellforgepy/issues
Project-URL: Examples, https://github.com/m-emm/shellforgepy/tree/main/examples
Platform: any
Classifier: Development Status :: 4 - Beta
Classifier: Programming Language :: Python
Classifier: Programming Language :: Python :: 3
Classifier: Programming Language :: Python :: 3.11
Classifier: Programming Language :: Python :: 3.12
Classifier: Intended Audience :: Developers
Classifier: Intended Audience :: Manufacturing
Classifier: Intended Audience :: Science/Research
Classifier: License :: OSI Approved :: MIT License
Classifier: Operating System :: OS Independent
Classifier: Topic :: Scientific/Engineering
Classifier: Topic :: Software Development :: Libraries :: Python Modules
Requires-Python: >=3.11
License-File: LICENSE.txt
Requires-Dist: importlib-metadata; python_version < "3.8"
Requires-Dist: numpy
Requires-Dist: scipy
Requires-Dist: networkx
Requires-Dist: PyYAML
Requires-Dist: requests
Requires-Dist: requests-toolbelt
Provides-Extra: cadquery
Requires-Dist: cadquery>=2.4; extra == "cadquery"
Provides-Extra: freecad
Provides-Extra: all
Requires-Dist: cadquery>=2.4; extra == "all"
Provides-Extra: testing
Requires-Dist: setuptools; extra == "testing"
Requires-Dist: pytest; extra == "testing"
Requires-Dist: pytest-cov; extra == "testing"
Dynamic: license-file
